django_pdf_actions/__init__.py
django_pdf_actions/actions/__init__.py
django_pdf_actions/actions/landscape.py
django_pdf_actions/actions/portrait.py
django_pdf_actions/actions/utils.py
django_pdf_actions/admin.py
django_pdf_actions/apps.py
django_pdf_actions/management/__init__.py
django_pdf_actions/management/commands/__init__.py
django_pdf_actions/management/commands/setup_fonts.py
django_pdf_actions/migrations/0001_initial.py
django_pdf_actions/migrations/0002_add_page_size_field.py
django_pdf_actions/migrations/0003_exportpdfsettings_rtl_support_and_more.py
django_pdf_actions/migrations/0004_add_alignment_fields.py
django_pdf_actions/migrations/__init__.py
django_pdf_actions/models.py
django_pdf_actions/tests.py
django_pdf_actions/views.py
django_pdf_actions-0.1.52.dist-info/LICENSE
django_pdf_actions-0.1.52.dist-info/METADATA
django_pdf_actions-0.1.52.dist-info/WHEEL
django_pdf_actions-0.1.52.dist-info/RECORD
