Metadata-Version: 2.3
Name: django-pdf-actions
Version: 0.1.52
Summary: A Django app to export PDFs from admin actions
License: MIT
Keywords: django,pdf,admin,export
Author: Ibrahim Roshdy
Author-email: ibrahimrosh5@gmail.com
Requires-Python: >=3.8
Classifier: Development Status :: 5 - Production/Stable
Classifier: Environment :: Web Environment
Classifier: Framework :: Django
Classifier: Framework :: Django :: 3.2
Classifier: Framework :: Django :: 4.0
Classifier: Framework :: Django :: 4.1
Classifier: Framework :: Django :: 4.2
Classifier: Framework :: Django :: 5.0
Classifier: Intended Audience :: Developers
Classifier: License :: OSI Approved :: MIT License
Classifier: Operating System :: OS Independent
Classifier: Programming Language :: Python :: 3
Classifier: Programming Language :: Python :: 3.8
Classifier: Programming Language :: Python :: 3.9
Classifier: Programming Language :: Python :: 3.10
Classifier: Programming Language :: Python :: 3.11
Classifier: Programming Language :: Python :: 3.12
Classifier: Programming Language :: Python :: 3.13
Classifier: Topic :: Software Development :: Libraries :: Python Modules
Requires-Dist: Django (>=3.2)
Requires-Dist: arabic-reshaper (>=3.0.0,<4.0.0)
Requires-Dist: django-model-utils (>=4.0.0)
Requires-Dist: python-bidi (>=0.4.0)
Requires-Dist: reportlab (>=4.0.4,<5.0.0)
Project-URL: Documentation, https://ibrahimroshdy.github.io/django-pdf-actions
Project-URL: Homepage, https://github.com/ibrahimroshdy/django-pdf-actions
Project-URL: Repository, https://github.com/ibrahimroshdy/django-pdf-actions
